LICENSE.txt
MANIFEST.in
README.md
setup.cfg
setup.py
vbarongdatools001/Vbalog.pyd
vbarongdatools001/Vbalogpy.py
vbarongdatools001/__init__.py
vbarongdatools001/vbaLogin.pyd
vbarongdatools001/vbaloginpy.py
vbarongdatools001/vbarongdatools001.pyd
vbarongdatools001/批量移动或重命名文件、创建文件夹-V0003.xlsm
vbarongdatools001.egg-info/PKG-INFO
vbarongdatools001.egg-info/SOURCES.txt
vbarongdatools001.egg-info/dependency_links.txt
vbarongdatools001.egg-info/top_level.txt